README.md
setup.cfg
setup.py
test/test_calculation_detail.py
test/test_check_result.py
test/test_cluster.py
test/test_cluster_api.py
test/test_cluster_assumptions.py
test/test_cluster_limits.py
test/test_cluster_point.py
test/test_cluster_result.py
test/test_cluster_settings.py
test/test_cluster_task.py
test/test_inline_response400.py
test/test_inline_response401.py
test/test_inline_response403.py
test/test_inline_response404.py
test/test_inline_response415.py
test/test_inline_response429.py
test/test_inline_response500.py
test/test_inline_response501.py
test/test_inline_response502.py
test/test_inline_response503.py
test/test_inline_response504.py
test/test_inline_response_default.py
test/test_location.py
test/test_matrix_line.py
test/test_performer.py
test/test_plan_id.py
test/test_plan_info.py
test/test_plan_status.py
test/test_routing.py
test/test_routing_matrix.py
test/test_system_api.py
test/test_time_window.py
test/test_trace_data.py
test/test_traffic_factor.py
test/test_transport_factor.py
test/test_transport_type.py
test/test_unclustered_point.py
test/test_validate_api.py
test/test_validate_result.py
test/test_validation.py
test/test_version_result.py
test/test_waypoint.py
vrt_lss_clustering/__init__.py
vrt_lss_clustering/api_client.py
vrt_lss_clustering/configuration.py
vrt_lss_clustering/exceptions.py
vrt_lss_clustering/model_utils.py
vrt_lss_clustering/rest.py
vrt_lss_clustering.egg-info/PKG-INFO
vrt_lss_clustering.egg-info/SOURCES.txt
vrt_lss_clustering.egg-info/dependency_links.txt
vrt_lss_clustering.egg-info/requires.txt
vrt_lss_clustering.egg-info/top_level.txt
vrt_lss_clustering/api/__init__.py
vrt_lss_clustering/api/cluster_api.py
vrt_lss_clustering/api/system_api.py
vrt_lss_clustering/api/validate_api.py
vrt_lss_clustering/apis/__init__.py
vrt_lss_clustering/model/__init__.py
vrt_lss_clustering/model/calculation_detail.py
vrt_lss_clustering/model/check_result.py
vrt_lss_clustering/model/cluster.py
vrt_lss_clustering/model/cluster_assumptions.py
vrt_lss_clustering/model/cluster_limits.py
vrt_lss_clustering/model/cluster_point.py
vrt_lss_clustering/model/cluster_result.py
vrt_lss_clustering/model/cluster_settings.py
